culturgen/__init__.py
culturgen-0.1.2.dist-info/LICENSE
culturgen-0.1.2.dist-info/METADATA
culturgen-0.1.2.dist-info/WHEEL
culturgen-0.1.2.dist-info/top_level.txt
culturgen-0.1.2.dist-info/RECORD
