Metadata-Version: 2.2
Name: culturgen
Version: 0.1.2
Summary: Know Your Meme scraper, a rewrite of memedict.
Author-email: dgw <dgw@technobabbl.es>
License: MIT
Project-URL: Homepage, https://github.com/dgw/culturgen
Project-URL: Bug Tracker, https://github.com/dgw/culturgen/issues
Classifier: Development Status :: 5 - Production/Stable
Classifier: Intended Audience :: Developers
Classifier: License :: OSI Approved :: MIT License
Classifier: Programming Language :: Python :: 3 :: Only
Classifier: Programming Language :: Python :: 3.9
Classifier: Programming Language :: Python :: 3.10
Classifier: Programming Language :: Python :: 3.11
Classifier: Programming Language :: Python :: 3.12
Classifier: Programming Language :: Python :: 3.13
Classifier: Topic :: Communications :: Chat
Classifier: Topic :: Software Development :: Libraries
License-File: LICENSE
Requires-Dist: requests>=2.10
Requires-Dist: beautifulsoup4>=4.5
